RSPileScripting/GraphingOptionsEnums.py
RSPileScripting/PileResults.py
RSPileScripting/RSPileModel.py
RSPileScripting/RSPileModeler.py
RSPileScripting/ResultsTable.py
RSPileScripting/__init__.py
RSPileScripting/_client.py
RSPileScripting/enums.py
RSPileScripting/PileSection/BoredCapacity.py
RSPileScripting/PileSection/DrivenCapacity.py
RSPileScripting/PileSection/Elastic.py
RSPileScripting/PileSection/HelicalCapacity.py
RSPileScripting/PileSection/PileAnalysis.py
RSPileScripting/PileSection/PileSection.py
RSPileScripting/PileSection/PileSectionEnums.py
RSPileScripting/PileSection/Plastic.py
RSPileScripting/PileSection/PrestressedConcrete.py
RSPileScripting/PileSection/ReinforcedConcrete.py
RSPileScripting/PileSection/__init__.py
RSPileScripting/PileSection/ConcreteDesigner/CasingBaseClass.py
RSPileScripting/PileSection/ConcreteDesigner/ConcreteDesignerEnumImports.py
RSPileScripting/PileSection/ConcreteDesigner/CoreBaseClass.py
RSPileScripting/PileSection/ConcreteDesigner/CustomReinforcementPattern.py
RSPileScripting/PileSection/ConcreteDesigner/IBeam.py
RSPileScripting/PileSection/ConcreteDesigner/IBeamEnums.py
RSPileScripting/PileSection/ConcreteDesigner/PrestressedConcreteCasing.py
RSPileScripting/PileSection/ConcreteDesigner/PrestressedConcreteCore.py
RSPileScripting/PileSection/ConcreteDesigner/PrestressedConcreteDesigner.py
RSPileScripting/PileSection/ConcreteDesigner/PrestressedConcreteReinforcement.py
RSPileScripting/PileSection/ConcreteDesigner/PrestressedConcreteReinforcementPattern.py
RSPileScripting/PileSection/ConcreteDesigner/RadialReinforcementPattern.py
RSPileScripting/PileSection/ConcreteDesigner/RectangleReinforcementPattern.py
RSPileScripting/PileSection/ConcreteDesigner/ReinforcedConcreteCasing.py
RSPileScripting/PileSection/ConcreteDesigner/ReinforcedConcreteCore.py
RSPileScripting/PileSection/ConcreteDesigner/ReinforcedConcreteDesigner.py
RSPileScripting/PileSection/ConcreteDesigner/ReinforcedConcreteReinforcement.py
rspilescripting-3.32.0.dist-info/METADATA
rspilescripting-3.32.0.dist-info/WHEEL
rspilescripting-3.32.0.dist-info/top_level.txt
rspilescripting-3.32.0.dist-info/RECORD
