Metadata-Version: 2.4
Name: RSPileScripting
Version: 3.32.0
Summary: Client library for interacting with RSPile through python
Author: Rocscience
License: MIT License
Project-URL: Homepage, https://www.rocscience.com/help/rspile/documentation/scripting/scripting-overview
Project-URL: Documentation, https://rocscience.github.io/rspile-scripting/
Keywords: Rocscience,RSPile,Scripting,RocScript,Geotechnical,Pile Analysis
Classifier: Programming Language :: Python :: 3
Classifier: License :: OSI Approved :: MIT License
Classifier: Topic :: Scientific/Engineering
Requires-Python: >=3.11
Requires-Dist: grpcio>=1.68.1
Requires-Dist: protobuf<6.0dev,>=5.26.1
Requires-Dist: pandas>=2.2.3
